mkdocs_asyncapi_tag/__init__.py
mkdocs_asyncapi_tag/mkdocs_asyncapi_plugin.py
tests/__init__.py
tests/test_asyncapi_plugin.py
mkdocs_asyncapi_tag_plugin-0.9.0.dist-info/LICENSE.txt
mkdocs_asyncapi_tag_plugin-0.9.0.dist-info/METADATA
mkdocs_asyncapi_tag_plugin-0.9.0.dist-info/WHEEL
mkdocs_asyncapi_tag_plugin-0.9.0.dist-info/entry_points.txt
mkdocs_asyncapi_tag_plugin-0.9.0.dist-info/top_level.txt
mkdocs_asyncapi_tag_plugin-0.9.0.dist-info/RECORD
