Metadata-Version: 2.1
Name: mkdocs-asyncapi-tag-plugin
Version: 0.9.0
Summary: MkDocs plugin to embed AsyncAPI HTML viewer in your markdown file.
Home-page: https://github.com/Weesho-Lapara/mkdocs-asyncapi-tag-plugin
Author: Weesho Lapara
Author-email: support@weesholapara.com
License: UNKNOWN
Keywords: mkdocs asyncapi,asyncapi render markdown
Platform: UNKNOWN
Requires-Dist: mkdocs (>=1.0.4)
Requires-Dist: beautifulsoup4 (>=4.6.0)
